{
  "verseOffset": 0,
  "prefix": "",
  "postfix": "",
  "eachVersePrefix": "[{n}]",
  "linkEndVerse": false,
  "useInvisibleLinks": true,
  "linkOnly": false,
  "newLines": true,
  "firstLinePrefix": "",
  "insertSpace": true,
  "oneVerseNotation": ":",
  "multipleVersesNotation": ":",
  "enableMultipleTranslations": true,
  "translationsPaths": "8 - Bibles/NKJV",
  "parsedTranslationPaths": [
    "8 - Bibles/NKJV/"
  ],
  "translationLinkingType": "used",
  "commentStart": "",
  "commentEnd": "",
  "outputBookMapString": "",
  "outputBookMap": {},
  "inputBookMapString": "Gen:Genesis\nGn:Genesis\n\nExo:Exodus\nEx:Exodus\n\nLev:Leviticus\nLv:Leviticus\n\nNum:Numbers\nNm:Numbers\n\nDeu:Deuteronomy\nDt:Deuteronomy\n\nJos:Joshua\nJosh:Joshua\n\nJudg:Judges\nJdg:Judges\n\nRut:Ruth\nRu:Ruth\n\n1Sa:1 Samuel\n1Sm:1 Samuel\n1Sam:1 Samuel\n\n2Sa:2 Samuel\n2Sm:2 Samuel\n2Sam:2 Samuel\n\n1Ki:1 Kings\n1Kg:1 Kings\n1Kn:1 Kings\n\n2Ki:2 Kings\n2Kg:2 Kings\n2Kn:2 Kings\n\n1Ch:1 Chronicles\n1Chr:1 Chronicles\n\n2Ch:2 Chronicles\n2Chr:2 Chronicles\n\nEzr:Ezra\n\nNeh:Nehemiah\nNehm:Nehemiah\n\nEst:Esther\nEsth:Esther\n\nJob:Job\n\nPsa:Psalms\nPs:Psalms\n\nPro:Proverbs\nPrv:Proverbs\n\nEcc:Ecclesiastes\nEccl:Ecclesiastes\n\nSon:Song of Solomon\nSg:Song of Solomon\nSoS:Song of Solomon\n\nIsa:Isaiah\nIs:Isaiah\n\nJer:Jeremiah\nJe:Jeremiah\n\nLam:Lamentations\nLam: Lamentations\n\nEze:Ezekiel\nEzk:Ezekiel\n\nDan:Daniel\nDn:Daniel\n\nHos:Hosea\nHo:Hosea\n\nJoe:Joel\nJl:Joel\n\nAmo:Amos\nAm:Amos\n\nOba:Obadiah\nOb:Obadiah\n\nJon:Jonah\nJonh:Jonah\n\nMic:Micah\nMc:Micah\n\nNah:Nahum\nNa:Nahum\n\nHab:Habakkuk\nHb:Habakkuk\n\nZep:Zephaniah\nZp:Zephaniah\n\nHag:Haggai\n\nZec:Zechariah\nZech:Zechariah\n\nMal:Malachi\nMl:Malachi\n\nMat:Matthew\nMt:Matthew\n\nMar:Mark\nMk:Mark\n\nLuk:Luke\nLk:Luke\n\nJoh:John\nJn:John\n\nAct:Acts\n\nRom:Romans\nRo:Romans\n\n1Co:1 Corinthians\n1Cor:1 Corinthians\n\n2Co:2 Corinthians\n2Cor:2 Corinthians\n\nGal:Galatians\nGa:Galatians\n\nEph:Ephesians\n\nPhi:Philippians\nPhil:Philippians\n\nCol:Colossians\nCo:Colossians\n\n1Th:1 Thessalonians\n1Thes:1 Thessalonians\n\n2Th:2 Thessalonians\n2Thes:2 Thessalonians\n\n1Ti:1 Timothy\n1Tim:1 Timothy\n\n2Ti:2 Timothy\n2Tim:2 Timothy\n\nTit:Titus\n\nPhm:Philemon\nPhlm:Philemon\n\nHeb:Hebrews\n\nJam:James\nJas:James\n\n1Pe:1 Peter\n1Pet:1 Peter\n\n2Pe:2 Peter\n2Pet:2 Peter\n\n1Jo:1 John\n1Jn:1 John\n\n2Jo:2 John\n2Jn:2 John\n\n3Jo:3 John\n3Jn:3 John\n\nJud:Jude\n\nRev:Revelation\nRe:Revelation\n",
  "inputBookMap": {
    "gen": "Genesis",
    "gn": "Genesis",
    "exo": "Exodus",
    "ex": "Exodus",
    "lev": "Leviticus",
    "lv": "Leviticus",
    "num": "Numbers",
    "nm": "Numbers",
    "deu": "Deuteronomy",
    "dt": "Deuteronomy",
    "jos": "Joshua",
    "josh": "Joshua",
    "judg": "Judges",
    "jdg": "Judges",
    "rut": "Ruth",
    "ru": "Ruth",
    "1sa": "1 Samuel",
    "1sm": "1 Samuel",
    "1sam": "1 Samuel",
    "2sa": "2 Samuel",
    "2sm": "2 Samuel",
    "2sam": "2 Samuel",
    "1ki": "1 Kings",
    "1kg": "1 Kings",
    "1kn": "1 Kings",
    "2ki": "2 Kings",
    "2kg": "2 Kings",
    "2kn": "2 Kings",
    "1ch": "1 Chronicles",
    "1chr": "1 Chronicles",
    "2ch": "2 Chronicles",
    "2chr": "2 Chronicles",
    "ezr": "Ezra",
    "neh": "Nehemiah",
    "nehm": "Nehemiah",
    "est": "Esther",
    "esth": "Esther",
    "job": "Job",
    "psa": "Psalms",
    "ps": "Psalms",
    "pro": "Proverbs",
    "prv": "Proverbs",
    "ecc": "Ecclesiastes",
    "eccl": "Ecclesiastes",
    "son": "Song of Solomon",
    "sg": "Song of Solomon",
    "sos": "Song of Solomon",
    "isa": "Isaiah",
    "is": "Isaiah",
    "jer": "Jeremiah",
    "je": "Jeremiah",
    "lam": " Lamentations",
    "eze": "Ezekiel",
    "ezk": "Ezekiel",
    "dan": "Daniel",
    "dn": "Daniel",
    "hos": "Hosea",
    "ho": "Hosea",
    "joe": "Joel",
    "jl": "Joel",
    "amo": "Amos",
    "am": "Amos",
    "oba": "Obadiah",
    "ob": "Obadiah",
    "jon": "Jonah",
    "jonh": "Jonah",
    "mic": "Micah",
    "mc": "Micah",
    "nah": "Nahum",
    "na": "Nahum",
    "hab": "Habakkuk",
    "hb": "Habakkuk",
    "zep": "Zephaniah",
    "zp": "Zephaniah",
    "hag": "Haggai",
    "zec": "Zechariah",
    "zech": "Zechariah",
    "mal": "Malachi",
    "ml": "Malachi",
    "mat": "Matthew",
    "mt": "Matthew",
    "mar": "Mark",
    "mk": "Mark",
    "luk": "Luke",
    "lk": "Luke",
    "joh": "John",
    "jn": "John",
    "act": "Acts",
    "rom": "Romans",
    "ro": "Romans",
    "1co": "1 Corinthians",
    "1cor": "1 Corinthians",
    "2co": "2 Corinthians",
    "2cor": "2 Corinthians",
    "gal": "Galatians",
    "ga": "Galatians",
    "eph": "Ephesians",
    "phi": "Philippians",
    "phil": "Philippians",
    "col": "Colossians",
    "co": "Colossians",
    "1th": "1 Thessalonians",
    "1thes": "1 Thessalonians",
    "2th": "2 Thessalonians",
    "2thes": "2 Thessalonians",
    "1ti": "1 Timothy",
    "1tim": "1 Timothy",
    "2ti": "2 Timothy",
    "2tim": "2 Timothy",
    "tit": "Titus",
    "phm": "Philemon",
    "phlm": "Philemon",
    "heb": "Hebrews",
    "jam": "James",
    "jas": "James",
    "1pe": "1 Peter",
    "1pet": "1 Peter",
    "2pe": "2 Peter",
    "2pet": "2 Peter",
    "1jo": "1 John",
    "1jn": "1 John",
    "2jo": "2 John",
    "2jn": "2 John",
    "3jo": "3 John",
    "3jn": "3 John",
    "jud": "Jude",
    "rev": "Revelation",
    "re": "Revelation"
  },
  "linkSeparator": "#",
  "versePrefix": "",
  "linkTypePreset": "Basic",
  "newLinePreset": true,
  "shouldCapitalizeBookNames": true,
  "verifyFilesWhenLinking": false
}